{
  "orc_chieftain": {
    "name": "Orc Chieftain",
    "hp": 720,
    "attack": 132,
    "defense": 60,
    "speed": 12,
    "description": "The brutal leader of the orc clan in the Deep Woods, wielding a massive war axe.",
    "special_abilities": [
      {
        "name": "War Cry",
        "description": "Roars to boost its own attack and intimidate the enemy",
        "attack_bonus": 8,
        "enemy_attack_penalty": 5,
        "duration": 5,
        "mp_cost": 10,
        "cooldown": 4
      },
      {
        "name": "Heavy Strike",
        "description": "A devastating blow that ignores some defense",
        "damage": 35,
        "defense_ignore": 0.5,
        "mp_cost": 0,
        "cooldown": 3
      }
    ],
    "phases": [
      {
        "hp_threshold": 0.4,
        "description": "Wounded but still fierce, the Chieftain fights with increased desperation",
        "attack_multiplier": 1.3,
        "special_abilities_unlocked": [
          "War Cry",
          "Heavy Strike"
        ]
      }
    ],
    "experience_reward": 200,
    "gold_reward": 100,
    "unique_loot": [
      "Chieftain's Axe",
      "Orc War Banner",
      "Bone Necklace"
    ],
    "unlock_conditions": {
      "level": 3,
      "missions_required": [
        "orc_invasion"
      ]
    },
    "tags": [
      "humanoid",
      "strong",
      "armored"
    ]
  },
  "goblin_king": {
    "name": "Goblin King",
    "hp": 840,
    "attack": 120,
    "defense": 48,
    "speed": 14,
    "description": "The greedy and cunning ruler of the goblin cave, wielding a dagger made from stolen treasures.",
    "special_abilities": [
      {
        "name": "Backstab",
        "description": "A sneaky attack from behind dealing critical damage",
        "damage": 35,
        "critical_chance": 0.4,
        "mp_cost": 0,
        "cooldown": 3
      },
      {
        "name": "Summon Minions",
        "description": "Calls forth goblin minions to aid in battle",
        "effect": "summon",
        "summon_count": 2,
        "summon_type": "goblin",
        "mp_cost": 20,
        "cooldown": 5
      },
      {
        "name": "Gold Toss",
        "description": "Throws stolen gold coins to distract and damage enemies",
        "damage": 15,
        "hit_count": 3,
        "mp_cost": 10,
        "cooldown": 2
      }
    ],
    "phases": [
      {
        "hp_threshold": 0.5,
        "description": "The Goblin King becomes desperate and calls for help",
        "attack_multiplier": 1.1,
        "special_abilities_unlocked": [
          "Summon Minions"
        ]
      },
      {
        "hp_threshold": 0.25,
        "description": "Cornered and furious, the King fights with all his cunning",
        "attack_multiplier": 1.3,
        "special_abilities_unlocked": [
          "Backstab",
          "Gold Toss"
        ]
      }
    ],
    "experience_reward": 250,
    "gold_reward": 120,
    "unique_loot": [
      "Goblin King's Dagger",
      "Stolen Gold Necklace",
      "Crown of Greed"
    ],
    "unlock_conditions": {
      "level": 4,
      "missions_required": [
        "forest_cleaning"
      ]
    },
    "tags": [
      "humanoid",
      "small",
      "spellcaster"
    ]
  },
  "troll_king": {
    "name": "Troll King",
    "hp": 1600,
    "attack": 224,
    "defense": 144,
    "speed": 8,
    "description": "The massive ruler of the underground tombs. Its enormous size and incredible strength make it a formidable opponent.",
    "special_abilities": [
      {
        "name": "Earthquake Slam",
        "description": "Slams the ground, dealing damage and potentially stunning the player",
        "damage": 35,
        "stun_chance": 0.4,
        "mp_cost": 0,
        "cooldown": 3
      },
      {
        "name": "Regeneration",
        "description": "Rapidly heals a portion of its health",
        "heal_amount": 40,
        "mp_cost": 25,
        "cooldown": 5
      }
    ],
    "phases": [
      {
        "hp_threshold": 0.5,
        "description": "The Troll King becomes more vicious as it takes damage",
        "attack_multiplier": 1.2,
        "regeneration_enabled": true
      }
    ],
    "experience_reward": 400,
    "gold_reward": 200,
    "unique_loot": [
      "Troll Club",
      "Troll King's Crown",
      "Earth Crystal"
    ],
    "unlock_conditions": {
      "level": 6,
      "missions_required": [
        "undead_horde"
      ]
    },
    "tags": [
      "giant",
      "humanoid",
      "regenerating"
    ]
  },
  "shadow_lord": {
    "name": "Shadow Lord",
    "hp": 1800,
    "attack": 300,
    "defense": 120,
    "speed": 18,
    "description": "A mysterious entity of pure darkness that rules the deepest parts of the ancient ruins.",
    "special_abilities": [
      {
        "name": "Shadow Strike",
        "description": "A lightning-fast attack that pierces all defenses",
        "damage": 45,
        "ignores_defense": true,
        "mp_cost": 20,
        "cooldown": 2
      },
      {
        "name": "Dark Portal",
        "description": "Summons shadows to aid in battle",
        "effect": "summon_shadows",
        "shadow_count": 2,
        "mp_cost": 30,
        "cooldown": 4
      },
      {
        "name": "Soul Drain",
        "description": "Drains the player's life force to heal itself",
        "damage": 30,
        "heal_amount": 20,
        "mp_cost": 25,
        "cooldown": 3
      }
    ],
    "phases": [
      {
        "hp_threshold": 0.6,
        "description": "The Shadow Lord reveals its true power",
        "attack_multiplier": 1.1,
        "special_abilities_unlocked": [
          "Shadow Strike"
        ]
      },
      {
        "hp_threshold": 0.3,
        "description": "Desperate and dangerous, the Shadow Lord uses all its dark powers",
        "attack_multiplier": 1.4,
        "special_abilities_unlocked": [
          "Shadow Strike",
          "Dark Portal",
          "Soul Drain"
        ]
      }
    ],
    "experience_reward": 350,
    "gold_reward": 175,
    "unique_loot": [
      "Shadow Blade",
      "Void Crystal",
      "Dark Lord's Cloak",
      "Soul Gem"
    ],
    "unlock_conditions": {
      "level": 7,
      "missions_required": [
        "ancient_artifact"
      ]
    },
    "tags": [
      "undead",
      "void",
      "spectral",
      "spellcaster"
    ]
  },
  "ice_queen": {
    "name": "Ice Queen",
    "hp": 1280,
    "attack": 200,
    "defense": 120,
    "speed": 20,
    "description": "The ethereal ruler of the Crystal Caves, she commands the power of eternal winter.",
    "special_abilities": [
      {
        "name": "Blizzard",
        "description": "A magical attack that freezes the enemy, reducing their speed",
        "damage": 30,
        "speed_reduction": 5,
        "duration": 3,
        "mp_cost": 20,
        "cooldown": 3
      },
      {
        "name": "Ice Shield",
        "description": "Creates a protective barrier that reduces incoming damage",
        "defense_bonus": 10,
        "duration": 4,
        "mp_cost": 15,
        "cooldown": 5
      },
      {
        "name": "Frost Nova",
        "description": "Releases a burst of freezing energy",
        "damage": 35,
        "freeze_chance": 0.5,
        "mp_cost": 25,
        "cooldown": 4
      }
    ],
    "phases": [
      {
        "hp_threshold": 0.5,
        "description": "The Ice Queen becomes more aggressive in defense of her domain",
        "attack_multiplier": 1.2,
        "special_abilities_unlocked": [
          "Ice Shield"
        ]
      },
      {
        "hp_threshold": 0.25,
        "description": "Desperation fuels her magical abilities",
        "attack_multiplier": 1.3,
        "special_abilities_unlocked": [
          "Blizzard",
          "Ice Shield",
          "Frost Nova"
        ]
      }
    ],
    "experience_reward": 300,
    "gold_reward": 150,
    "unique_loot": [
      "Ice Queen's Crown",
      "Boreas",
      "Crystal of Eternal Winter"
    ],
    "unlock_conditions": {
      "level": 5,
      "missions_required": [
        "crystal_guardian"
      ]
    },
    "tags": [
      "humanoid",
      "ice",
      "cold",
      "spellcaster"
    ]
  },
  "necromancer_lord": {
    "name": "Necromancer Lord Vorthak",
    "hp": 1440,
    "attack": 224,
    "defense": 80,
    "speed": 16,
    "description": "A master of dark magic who commands the undead from his throne deep within the Underground Tombs.",
    "special_abilities": [
      {
        "name": "Army of the Dead",
        "description": "Summons skeletal warriors to fight alongside",
        "effect": "summon_undead",
        "undead_count": 3,
        "undead_type": "skeleton_warrior",
        "mp_cost": 30,
        "cooldown": 5
      },
      {
        "name": "Soul Harvest",
        "description": "Drains the life force of enemies to heal",
        "damage": 25,
        "heal_amount": 30,
        "mp_cost": 20,
        "cooldown": 3
      },
      {
        "name": "Death Curse",
        "description": "Curses an enemy, causing damage over time",
        "damage": 8,
        "duration": 6,
        "mp_cost": 25,
        "cooldown": 4
      },
      {
        "name": "Bone Shield",
        "description": "Summons skeletal arms to block incoming attacks",
        "defense_bonus": 15,
        "duration": 4,
        "mp_cost": 20,
        "cooldown": 5
      }
    ],
    "phases": [
      {
        "hp_threshold": 0.6,
        "description": "The necromancer begins to summon his undead army",
        "attack_multiplier": 1.0,
        "special_abilities_unlocked": [
          "Death Curse"
        ]
      },
      {
        "hp_threshold": 0.3,
        "description": "Desperate, Vorthak unleashes his full dark power",
        "attack_multiplier": 1.3,
        "special_abilities_unlocked": [
          "Army of the Dead",
          "Soul Harvest",
          "Bone Shield"
        ]
      }
    ],
    "experience_reward": 400,
    "gold_reward": 220,
    "unique_loot": [
      "Necromancer's Robes",
      "Skull Staff",
      "Soul Orb",
      "Bone Crown",
      "Cursed Amulet"
    ],
    "unlock_conditions": {
      "level": 6,
      "missions_required": [
        "troll_slayer"
      ]
    },
    "tags": [
      "humanoid",
      "undead",
      "spellcaster"
    ]
  },
  "fire_dragon_boss": {
    "name": "Ancient Fire Dragon",
    "hp": 3000,
    "attack": 350,
    "defense": 200,
    "speed": 15,
    "description": "The legendary Ancient Fire Dragon, ruler of the crystal mountains. Its breath can melt stone and its roar shakes the very earth.",
    "special_abilities": [
      {
        "name": "Fire Breath",
        "description": "Deals massive fire damage to all enemies",
        "damage": 50,
        "mp_cost": 20,
        "cooldown": 3
      },
      {
        "name": "Dragon Roar",
        "description": "Intimidates enemies, reducing their attack and defense",
        "effect": "debuff",
        "attack_reduction": 10,
        "defense_reduction": 5,
        "duration": 5,
        "mp_cost": 15,
        "cooldown": 4
      },
      {
        "name": "Wing Buffet",
        "description": "A powerful physical attack that may stun the enemy",
        "damage": 40,
        "stun_chance": 0.3,
        "mp_cost": 0,
        "cooldown": 2
      }
    ],
    "phases": [
      {
        "hp_threshold": 0.7,
        "description": "The dragon fights with typical draconic fury",
        "attack_multiplier": 1.0
      },
      {
        "hp_threshold": 0.4,
        "description": "Enraged by its wounds, the dragon becomes more aggressive",
        "attack_multiplier": 1.3,
        "defense_multiplier": 0.8
      },
      {
        "hp_threshold": 0.2,
        "description": "In its final moments, the dragon unleashes all its power",
        "attack_multiplier": 1.5,
        "defense_multiplier": 0.6,
        "special_abilities_unlocked": [
          "Fire Breath",
          "Dragon Roar"
        ]
      }
    ],
    "experience_reward": 1000,
    "gold_reward": 500,
    "unique_loot": [
      "Dragon Scale Armor",
      "Fire Gem",
      "Dragon Heart",
      "Ancient Dragon Scale"
    ],
    "unlock_conditions": {
      "level": 8,
      "missions_required": [
        "crystal_guardian",
        "troll_slayer"
      ]
    },
    "dialogues": {
      "on_start_battle": "dragon.boss.start",
      "on_defeat": "dragon.boss.defeat"
    },
    "tags": [
      "dragon",
      "fire",
      "flying",
      "large"
    ]
  }
}
